LICENSE.txt
MANIFEST.in
README.md
setup.cfg
setup.py
nefit/__init__.py
nefit/cli.py
nefit/core.py
nefit/exceptions.py
nefit/version.py
nefit_client.egg-info/PKG-INFO
nefit_client.egg-info/SOURCES.txt
nefit_client.egg-info/dependency_links.txt
nefit_client.egg-info/entry_points.txt
nefit_client.egg-info/requires.txt
nefit_client.egg-info/top_level.txt