Metadata-Version: 2.1
Name: nefit-client
Version: 0.3.0
Summary: Python API and command line tool for talking to the Nefit Easy™ Thermostat
Home-page: https://github.com/patvdleer/nefit-client-python.git
Author: Patrick van der Leer
Author-email: pat.vdleer@gmail.com
Maintainer: Patrick van der Leer
Maintainer-email: pat.vdleer@gmail.com
License: MIT
Download-URL: https://github.com/patvdleer/nefit-client-python/archive/v0.3.0.tar.gz
Platform: UNKNOWN
Classifier: Development Status :: 3 - Alpha
Classifier: Intended Audience :: Developers
Classifier: Intended Audience :: End Users/Desktop
Classifier: License :: OSI Approved :: MIT License
Classifier: Environment :: Console
Classifier: Topic :: Other/Nonlisted Topic
Classifier: Topic :: Utilities
Classifier: Topic :: Software Development :: Libraries :: Python Modules
Classifier: Programming Language :: Python
Classifier: Programming Language :: Python :: 3
Classifier: Programming Language :: Python :: 3.2
Classifier: Programming Language :: Python :: 3.3
Classifier: Programming Language :: Python :: 3.4
Classifier: Programming Language :: Python :: 3.5
Classifier: Programming Language :: Python :: 3.6
Classifier: Programming Language :: Python :: 3.7
Classifier: Programming Language :: Python :: 3.8
Classifier: Programming Language :: Python :: 3 :: Only
